{
  "annotations": {
    "list": [
      {
        "builtIn": 1,
        "datasource": {
          "type": "grafana",
          "uid": "-- Grafana --"
        },
        "enable": true,
        "hide": true,
        "iconColor": "rgba(0, 211, 255, 1)",
        "name": "Annotations & Alerts",
        "type": "dashboard"
      }
    ]
  },
  "editable": true,
  "fiscalYearStartMonth": 0,
  "graphTooltip": 0,
  "id": null,
  "links": [],
  "liveNow": false,
  "panels": [
    {
      "datasource": {
        "type": "elasticsearch",
        "uid": "P31C819B24CF3C3C7"
      },
      "fieldConfig": {
        "defaults": {
          "color": {
            "mode": "palette-classic"
          },
          "custom": {
            "axisLabel": "",
            "axisPlacement": "auto",
            "barAlignment": 0,
            "drawStyle": "line",
            "fillOpacity": 10,
            "gradientMode": "none",
            "hideFrom": {
              "legend": false,
              "tooltip": false,
              "vis": false
            },
            "lineInterpolation": "linear",
            "lineWidth": 1,
            "pointSize": 5,
            "scaleDistribution": {
              "type": "linear"
            },
            "showPoints": "never",
            "spanNulls": false,
            "stacking": {
              "group": "A",
              "mode": "none"
            },
            "thresholdsStyle": {
              "mode": "off"
            }
          },
          "mappings": [],
          "thresholds": {
            "mode": "absolute",
            "steps": [
              {
                "color": "green",
                "value": null
              },
              {
                "color": "red",
                "value": 80
              }
            ]
          },
          "unit": "short"
        },
        "overrides": []
      },
      "gridPos": {
        "h": 8,
        "w": 12,
        "x": 0,
        "y": 0
      },
      "id": 1,
      "options": {
        "legend": {
          "calcs": [],
          "displayMode": "list",
          "placement": "bottom"
        },
        "tooltip": {
          "mode": "single",
          "sort": "none"
        }
      },
      "targets": [
        {
          "alias": "Log Volume",
          "bucketAggs": [
            {
              "field": "@timestamp",
              "id": "2",
              "settings": {
                "interval": "auto"
              },
              "type": "date_histogram"
            }
          ],
          "metrics": [
            {
              "id": "1",
              "type": "count"
            }
          ],
          "query": "*",
          "refId": "A",
          "timeField": "@timestamp"
        }
      ],
      "title": "Log Volume Over Time",
      "type": "timeseries"
    },
    {
      "datasource": {
        "type": "elasticsearch",
        "uid": "P31C819B24CF3C3C7"
      },
      "fieldConfig": {
        "defaults": {
          "color": {
            "mode": "palette-classic"
          },
          "custom": {
            "hideFrom": {
              "legend": false,
              "tooltip": false,
              "vis": false
            }
          },
          "mappings": []
        },
        "overrides": []
      },
      "gridPos": {
        "h": 8,
        "w": 12,
        "x": 12,
        "y": 0
      },
      "id": 2,
      "options": {
        "legend": {
          "displayMode": "list",
          "placement": "bottom"
        },
        "pieType": "pie",
        "reduceOptions": {
          "calcs": [
            "lastNotNull"
          ],
          "fields": "",
          "values": false
        },
        "tooltip": {
          "mode": "single",
          "sort": "none"
        }
      },
      "targets": [
        {
          "alias": "Log Levels",
          "bucketAggs": [
            {
              "field": "level.keyword",
              "id": "2",
              "type": "terms"
            }
          ],
          "metrics": [
            {
              "id": "1",
              "type": "count"
            }
          ],
          "query": "*",
          "refId": "A",
          "timeField": "@timestamp"
        }
      ],
      "title": "Log Levels Distribution",
      "type": "piechart"
    },
    {
      "datasource": {
        "type": "elasticsearch",
        "uid": "P31C819B24CF3C3C7"
      },
      "fieldConfig": {
        "defaults": {
          "color": {
            "mode": "palette-classic"
          },
          "custom": {
            "hideFrom": {
              "legend": false,
              "tooltip": false,
              "vis": false
            }
          },
          "mappings": []
        },
        "overrides": []
      },
      "gridPos": {
        "h": 8,
        "w": 12,
        "x": 0,
        "y": 8
      },
      "id": 3,
      "options": {
        "legend": {
          "displayMode": "list",
          "placement": "bottom"
        },
        "pieType": "pie",
        "reduceOptions": {
          "calcs": [
            "lastNotNull"
          ],
          "fields": "",
          "values": false
        },
        "tooltip": {
          "mode": "single",
          "sort": "none"
        }
      },
      "targets": [
        {
          "alias": "Container Logs",
          "bucketAggs": [
            {
              "field": "container.keyword",
              "id": "2",
              "type": "terms"
            }
          ],
          "metrics": [
            {
              "id": "1",
              "type": "count"
            }
          ],
          "query": "*",
          "refId": "A",
          "timeField": "@timestamp"
        }
      ],
      "title": "Logs by Container",
      "type": "piechart"
    },
    {
      "datasource": {
        "type": "elasticsearch",
        "uid": "P31C819B24CF3C3C7"
      },
      "fieldConfig": {
        "defaults": {
          "color": {
            "mode": "palette-classic"
          },
          "custom": {
            "axisLabel": "",
            "axisPlacement": "auto",
            "barAlignment": 0,
            "drawStyle": "line",
            "fillOpacity": 10,
            "gradientMode": "none",
            "hideFrom": {
              "legend": false,
              "tooltip": false,
              "vis": false
            },
            "lineInterpolation": "linear",
            "lineWidth": 1,
            "pointSize": 5,
            "scaleDistribution": {
              "type": "linear"
            },
            "showPoints": "never",
            "spanNulls": false,
            "stacking": {
              "group": "A",
              "mode": "none"
            },
            "thresholdsStyle": {
              "mode": "off"
            }
          },
          "mappings": [],
          "thresholds": {
            "mode": "absolute",
            "steps": [
              {
                "color": "green",
                "value": null
              },
              {
                "color": "red",
                "value": 80
              }
            ]
          },
          "unit": "short"
        },
        "overrides": []
      },
      "gridPos": {
        "h": 8,
        "w": 12,
        "x": 12,
        "y": 8
      },
      "id": 4,
      "options": {
        "legend": {
          "calcs": [],
          "displayMode": "list",
          "placement": "bottom"
        },
        "tooltip": {
          "mode": "single",
          "sort": "none"
        }
      },
      "targets": [
        {
          "alias": "Error Rate",
          "bucketAggs": [
            {
              "field": "@timestamp",
              "id": "2",
              "settings": {
                "interval": "auto"
              },
              "type": "date_histogram"
            }
          ],
          "metrics": [
            {
              "id": "1",
              "type": "count"
            }
          ],
          "query": "level.keyword:ERROR",
          "refId": "A",
          "timeField": "@timestamp"
        }
      ],
      "title": "Error Rate Over Time",
      "type": "timeseries"
    },
    {
      "datasource": {
        "type": "elasticsearch",
        "uid": "P31C819B24CF3C3C7"
      },
      "gridPos": {
        "h": 12,
        "w": 24,
        "x": 0,
        "y": 16
      },
      "id": 5,
      "options": {
        "showLabels": false,
        "showTime": true,
        "sortOrder": "Descending",
        "wrapLogMessage": true,
        "prettifyLogMessage": true,
        "enableLogDetails": true,
        "dedupStrategy": "none"
      },
      "targets": [
        {
          "alias": "Recent Logs",
          "metrics": [
            {
              "id": "1",
              "type": "logs"
            }
          ],
          "query": "*",
          "refId": "A",
          "timeField": "@timestamp"
        }
      ],
      "title": "Recent Logs",
      "type": "logs"
    }
  ],
  "refresh": "5s",
  "schemaVersion": 27,
  "style": "dark",
  "tags": [
    "logs",
    "application",
    "elk"
  ],
  "templating": {
    "list": []
  },
  "time": {
    "from": "now-1h",
    "to": "now"
  },
  "timepicker": {},
  "timezone": "",
  "title": "Application Logs Dashboard",
  "uid": "app-logs",
  "version": 1
}
